Metadata-Version: 1.0
Name: distributions-FHF
Version: 0.1
Summary: Gaussian distributions
Home-page: UNKNOWN
Author: Federico Hellmund
Author-email: UNKNOWN
License: UNKNOWN
Platform: UNKNOWN
